<?xml version="1.0" encoding="utf-8"?>
<SoundBanksInfo Platform="Windows" BasePlatform="Windows" SchemaVersion="10" SoundbankVersion="113">
	<RootPaths>
		<ProjectRoot>F:\Gitstuff\barely-survived\Unity Project\Barely Survived\Barely Survived Wwise\</ProjectRoot>
		<SourceFilesRoot>F:\Gitstuff\barely-survived\Unity Project\Barely Survived\Barely Survived Wwise\.cache\Windows\</SourceFilesRoot>
		<SoundBanksRoot>F:\Gitstuff\barely-survived\Unity Project\Barely Survived\Barely Survived Wwise\GeneratedSoundBanks\Windows\</SoundBanksRoot>
		<ExternalSourcesInputFile></ExternalSourcesInputFile>
		<ExternalSourcesOutputRoot>F:\Gitstuff\barely-survived\Unity Project\Barely Survived\Barely Survived Wwise\GeneratedSoundBanks\Windows\</ExternalSourcesOutputRoot>
	</RootPaths>
	<DialogueEvents/>
	<StreamedFiles/>
	<MediaFilesNotInAnyBank/>
	<SoundBanks>
		<SoundBank Id="1355168291" Language="SFX">
			<ShortName>Init</ShortName>
			<Path>Init.bnk</Path>
		</SoundBank>
		<SoundBank Id="3157003241" Language="SFX">
			<ShortName>Test</ShortName>
			<Path>Test.bnk</Path>
			<IncludedEvents>
				<Event Id="1652966903" Name="death_scream"/>
				<Event Id="3849537216" Name="play_title"/>
				<Event Id="2370690330" Name="stop_title"/>
			</IncludedEvents>
			<IncludedMemoryFiles>
				<File Id="709327519" Language="SFX">
					<ShortName>Space MainTheme.wav</ShortName>
					<Path>SFX\Space MainTheme_4B8CC0C5.wem</Path>
				</File>
			</IncludedMemoryFiles>
		</SoundBank>
	</SoundBanks>
</SoundBanksInfo>
